finnsflask/__init__.py
finnsflask/finnsflask.py
finnsflask/httprequest.py
finnsflask/httpresponse.py
finnsflask/webserver.py
finnsflask-1.2.dist-info/LICENSE.txt
finnsflask-1.2.dist-info/METADATA
finnsflask-1.2.dist-info/WHEEL
finnsflask-1.2.dist-info/top_level.txt
finnsflask-1.2.dist-info/RECORD
